scrapbox/__init__.py
scrapbox/client.py
scrapbox/request.py
scrapbox/resource.py
scrapbox-0.6.1.dist-info/LICENSE
scrapbox-0.6.1.dist-info/METADATA
scrapbox-0.6.1.dist-info/WHEEL
scrapbox-0.6.1.dist-info/top_level.txt
scrapbox-0.6.1.dist-info/RECORD
