Metadata-Version: 2.1
Name: scrapbox
Version: 0.6.1
Summary: An unofficial wrapper around the Scrapbox API
Home-page: https://github.com/7ma7X/scrapbox-python
Author: HelloRusk
Author-email: 7X.rusk@gmail.com
License: MIT
Platform: UNKNOWN
Requires-Dist: requests
